setup.cfg
setup.py
BitEx.egg-info/PKG-INFO
BitEx.egg-info/SOURCES.txt
BitEx.egg-info/dependency_links.txt
BitEx.egg-info/requires.txt
BitEx.egg-info/top_level.txt
bitex/__init__.py
bitex/utils.py
bitex/api/__init__.py
bitex/api/response.py
bitex/api/REST/__init__.py
bitex/api/REST/api.py
bitex/api/REST/response.py
bitex/api/REST/rest.py
bitex/api/WSS/__init__.py
bitex/api/WSS/base.py
bitex/api/WSS/bitfinex.py
bitex/api/WSS/bitstamp.py
bitex/api/WSS/exceptions.py
bitex/api/WSS/gdax.py
bitex/api/WSS/gemini.py
bitex/api/WSS/hitbtc.py
bitex/api/WSS/okcoin.py
bitex/api/WSS/poloniex.py
bitex/formatters/__init__.py
bitex/formatters/base.py
bitex/formatters/bitfinex.py
bitex/formatters/bitstamp.py
bitex/formatters/bittrex.py
bitex/formatters/bter.py
bitex/formatters/ccex.py
bitex/formatters/coincheck.py
bitex/formatters/cryptopia.py
bitex/formatters/gdax.py
bitex/formatters/gemini.py
bitex/formatters/hitbtc.py
bitex/formatters/itbit.py
bitex/formatters/kraken.py
bitex/formatters/okcoin.py
bitex/formatters/poloniex.py
bitex/formatters/quadriga.py
bitex/formatters/quoine.py
bitex/formatters/rocktrading.py
bitex/formatters/vaultoro.py
bitex/formatters/yunbi.py
bitex/interfaces/__init__.py
bitex/interfaces/bitfinex.py
bitex/interfaces/bitstamp.py
bitex/interfaces/bittrex.py
bitex/interfaces/bter.py
bitex/interfaces/ccex.py
bitex/interfaces/coincheck.py
bitex/interfaces/cryptopia.py
bitex/interfaces/gdax.py
bitex/interfaces/gemini.py
bitex/interfaces/hitbtc.py
bitex/interfaces/itbit.py
bitex/interfaces/kraken.py
bitex/interfaces/okcoin.py
bitex/interfaces/poloniex.py
bitex/interfaces/quadriga.py
bitex/interfaces/quoine.py
bitex/interfaces/rocktrading.py
bitex/interfaces/vaultoro.py
bitex/interfaces/yunbi.py