Metadata-Version: 1.1
Name: BitEx
Version: 1.1.2
Summary: Python3-based API Framework for Crypto Exchanges
Home-page: https://github.com/nlsdfnbch/bitex.git
Author: Nils Diefenbach
Author-email: 23okrs20+pypi@mykolab.com
License: MIT
Platform: UNKNOWN
Classifier: Development Status :: 4 - Beta
Classifier: Intended Audience :: Developers
